jupyter_ai_tools/__init__.py
jupyter_ai_tools/utils.py
jupyter_ai_tools/toolkits/__init__.py
jupyter_ai_tools/toolkits/code_execution.py
jupyter_ai_tools/toolkits/file_system.py
jupyter_ai_tools/toolkits/git.py
jupyter_ai_tools/toolkits/notebook.py
jupyter_ai_tools-0.2.1.data/data/etc/jupyter/jupyter_server_config.d/jupyter_ai_tools.json
jupyter_ai_tools-0.2.1.dist-info/METADATA
jupyter_ai_tools-0.2.1.dist-info/WHEEL
jupyter_ai_tools-0.2.1.dist-info/entry_points.txt
jupyter_ai_tools-0.2.1.dist-info/licenses/LICENSE
jupyter_ai_tools-0.2.1.dist-info/RECORD
