Metadata-Version: 2.4
Name: jupyter_ai_tools
Version: 0.2.1
Project-URL: Home, https://github.com/Abigayle-Mercer/jupyter-ai-tools
Author-email: Abigayle Mercer <abigaylemercer@gmail.com>
License: BSD 3-Clause License
License-File: LICENSE
Keywords: Extension,Jupyter
Classifier: Framework :: Jupyter
Classifier: License :: OSI Approved :: BSD License
Classifier: Programming Language :: Python
Classifier: Programming Language :: Python :: 3
Classifier: Programming Language :: Python :: 3.8
Classifier: Programming Language :: Python :: 3.9
Classifier: Programming Language :: Python :: 3.10
Classifier: Programming Language :: Python :: 3.11
Requires-Python: >=3.9
Requires-Dist: jupyter-ai>=3.0.0-beta.1
Requires-Dist: jupyter-server<3,>=1.6
Requires-Dist: jupyterlab-git
Provides-Extra: lint
Requires-Dist: black>=22.6.0; extra == 'lint'
Requires-Dist: mdformat-gfm>=0.3.5; extra == 'lint'
Requires-Dist: mdformat>=0.7.16; extra == 'lint'
Requires-Dist: mypy>=0.990; extra == 'lint'
Requires-Dist: pydantic>=1.10; extra == 'lint'
Requires-Dist: ruff>=0.0.156; extra == 'lint'
Requires-Dist: types-jsonschema; extra == 'lint'
Provides-Extra: test
Requires-Dist: pytest-jupyter[server]>=0.6; extra == 'test'
Requires-Dist: pytest>=7.0; extra == 'test'
Provides-Extra: typing
Requires-Dist: mypy>=0.990; extra == 'typing'
